taichi_gpu_nightly-0.0.59.data/purelib/taichi/__init__.py
taichi_gpu_nightly-0.0.59.data/purelib/taichi/main.py
taichi_gpu_nightly-0.0.59.data/purelib/taichi/torch_io.py
taichi_gpu_nightly-0.0.59.data/purelib/taichi/core/__init__.py
taichi_gpu_nightly-0.0.59.data/purelib/taichi/core/unit.py
taichi_gpu_nightly-0.0.59.data/purelib/taichi/core/util.py
taichi_gpu_nightly-0.0.59.data/purelib/taichi/include/arithmetics.h
taichi_gpu_nightly-0.0.59.data/purelib/taichi/include/common.h
taichi_gpu_nightly-0.0.59.data/purelib/taichi/include/context.h
taichi_gpu_nightly-0.0.59.data/purelib/taichi/include/kernel.h
taichi_gpu_nightly-0.0.59.data/purelib/taichi/include/profiler.h
taichi_gpu_nightly-0.0.59.data/purelib/taichi/include/struct.h
taichi_gpu_nightly-0.0.59.data/purelib/taichi/include/unified_allocator.h
taichi_gpu_nightly-0.0.59.data/purelib/taichi/include/taichi/arithmetics.h
taichi_gpu_nightly-0.0.59.data/purelib/taichi/include/taichi/common.h
taichi_gpu_nightly-0.0.59.data/purelib/taichi/include/taichi/context.h
taichi_gpu_nightly-0.0.59.data/purelib/taichi/include/taichi/kernel.h
taichi_gpu_nightly-0.0.59.data/purelib/taichi/include/taichi/lang.h
taichi_gpu_nightly-0.0.59.data/purelib/taichi/include/taichi/profiler.h
taichi_gpu_nightly-0.0.59.data/purelib/taichi/include/taichi/struct.h
taichi_gpu_nightly-0.0.59.data/purelib/taichi/include/taichi/unified_allocator.h
taichi_gpu_nightly-0.0.59.data/purelib/taichi/lang/__init__.py
taichi_gpu_nightly-0.0.59.data/purelib/taichi/lang/core.py
taichi_gpu_nightly-0.0.59.data/purelib/taichi/lang/expr.py
taichi_gpu_nightly-0.0.59.data/purelib/taichi/lang/impl.py
taichi_gpu_nightly-0.0.59.data/purelib/taichi/lang/matrix.py
taichi_gpu_nightly-0.0.59.data/purelib/taichi/lang/snode.py
taichi_gpu_nightly-0.0.59.data/purelib/taichi/lang/tape.py
taichi_gpu_nightly-0.0.59.data/purelib/taichi/lang/transformer.py
taichi_gpu_nightly-0.0.59.data/purelib/taichi/lang/util.py
taichi_gpu_nightly-0.0.59.data/purelib/taichi/lib/taichi_core.so
taichi_gpu_nightly-0.0.59.dist-info/LICENSE.txt
taichi_gpu_nightly-0.0.59.dist-info/METADATA
taichi_gpu_nightly-0.0.59.dist-info/WHEEL
taichi_gpu_nightly-0.0.59.dist-info/top_level.txt
taichi_gpu_nightly-0.0.59.dist-info/RECORD
